[
    {
        "category_id": "1",
        "category_name": "Aliments & Gastrnomie",
        "fk_markers": "1"
    },
    {
        "category_id": "2",
        "category_name": "Tourisme",
        "fk_markers": "2"
    },
    {
        "category_id": "3",
        "category_name": "Sport & Loisirs",
        "fk_markers": "3"
    },
    {
        "category_id": "4",
        "category_name": "Magasins Spécialisés",
        "fk_markers": "4"
    },
    {
        "category_id": "5",
        "category_name": "Services",
        "fk_markers": "5"
    },
    {
        "category_id": "6",
        "category_name": "Bien-être & Santé",
        "fk_markers": "6"
    },
    {
        "category_id": "7",
        "category_name": "Autres",
        "fk_markers": "7"
    }
]